celluloid/__init__.py
celluloid/celluloid.py
celluloid_clust-1.2.5.dist-info/LICENSE
celluloid_clust-1.2.5.dist-info/METADATA
celluloid_clust-1.2.5.dist-info/WHEEL
celluloid_clust-1.2.5.dist-info/entry_points.txt
celluloid_clust-1.2.5.dist-info/top_level.txt
celluloid_clust-1.2.5.dist-info/RECORD
