Metadata-Version: 2.1
Name: celluloid-clust
Version: 1.2.5
Summary: Effective Clustering for Single Cell Sequencing Cancer Data
Home-page: https://github.com/AlgoLab/celluloid
Author: Murray Patterson
Author-email: mpatterson@cs.gsu.edu
License: UNKNOWN
Platform: UNKNOWN
Classifier: Programming Language :: Python :: 3
Classifier: License :: OSI Approved :: MIT License
Classifier: Operating System :: OS Independent
Requires-Python: >=3.6
Requires-Dist: TatSu (>=5.5.0)
Requires-Dist: kmodes (>=0.10.2)
